AppiumGuanfangWendang/README.md
AppiumGuanfangWendang/__init__.py
AppiumGuanfangWendang/__main__.py
AppiumGuanfangWendang/file.epub
AppiumGuanfangWendang/index.html
AppiumGuanfangWendang/css/__init__.py
AppiumGuanfangWendang/css/annotations.css
AppiumGuanfangWendang/css/main.css
AppiumGuanfangWendang/css/normalize.css
AppiumGuanfangWendang/css/popup.css
AppiumGuanfangWendang/font/__init__.py
AppiumGuanfangWendang/font/fontello.eot
AppiumGuanfangWendang/font/fontello.svg
AppiumGuanfangWendang/font/fontello.ttf
AppiumGuanfangWendang/font/fontello.woff
AppiumGuanfangWendang/img/__init__.py
AppiumGuanfangWendang/img/annotator-glyph-sprite.png
AppiumGuanfangWendang/img/annotator-icon-sprite.png
AppiumGuanfangWendang/img/apple-touch-icon.png
AppiumGuanfangWendang/img/cancelfullscreen.png
AppiumGuanfangWendang/img/close.png
AppiumGuanfangWendang/img/fullscreen.png
AppiumGuanfangWendang/img/loader.gif
AppiumGuanfangWendang/img/menu-icon.png
AppiumGuanfangWendang/img/save.png
AppiumGuanfangWendang/img/saved.png
AppiumGuanfangWendang/img/settings-s.png
AppiumGuanfangWendang/img/settings.png
AppiumGuanfangWendang/img/star.png
AppiumGuanfangWendang/js/__init__.py
AppiumGuanfangWendang/js/epub.js
AppiumGuanfangWendang/js/epub.min.js
AppiumGuanfangWendang/js/epub.min.map
AppiumGuanfangWendang/js/hooks.min.js
AppiumGuanfangWendang/js/hooks.min.map
AppiumGuanfangWendang/js/reader.js
AppiumGuanfangWendang/js/reader.js.map
AppiumGuanfangWendang/js/reader.min.js
AppiumGuanfangWendang/js/reader.min.map
AppiumGuanfangWendang/js/hooks/__init__.py
AppiumGuanfangWendang/js/hooks/extensions/__init__.py
AppiumGuanfangWendang/js/hooks/extensions/highlight.js
AppiumGuanfangWendang/js/libs/__init__.py
AppiumGuanfangWendang/js/libs/jquery.min.js
AppiumGuanfangWendang/js/libs/localforage.min.js
AppiumGuanfangWendang/js/libs/screenfull.js
AppiumGuanfangWendang/js/libs/screenfull.min.js
AppiumGuanfangWendang/js/libs/zip.min.js
AppiumGuanfangWendang/js/plugins/__init__.py
appium_guanfang_wendang-2024.3.6.0.dist-info/METADATA
appium_guanfang_wendang-2024.3.6.0.dist-info/WHEEL
appium_guanfang_wendang-2024.3.6.0.dist-info/entry_points.txt
appium_guanfang_wendang-2024.3.6.0.dist-info/top_level.txt
appium_guanfang_wendang-2024.3.6.0.dist-info/RECORD
